pyinspirationquotes/__init__.py
pyinspirationquotes/main.py
pyinspirationquotes/quotes.txt
pyinspirationquotes-1.0.5.dist-info/METADATA
pyinspirationquotes-1.0.5.dist-info/WHEEL
pyinspirationquotes-1.0.5.dist-info/entry_points.txt
pyinspirationquotes-1.0.5.dist-info/top_level.txt
pyinspirationquotes-1.0.5.dist-info/RECORD
