Metadata-Version: 2.4
Name: pyinspirationquotes
Version: 1.0.5
Summary: A simple and fun Python package that provides random inspirational quotes.
Home-page: https://github.com/akankshasoni024/pyinspirationquotes
Author: Akanksha Soni
Author-email: aakankshasoni024@gmail.com
Classifier: Development Status :: 5 - Production/Stable
Classifier: Intended Audience :: End Users/Desktop
Classifier: Topic :: Utilities
Classifier: Programming Language :: Python :: 3
Classifier: Programming Language :: Python :: 3.6
Classifier: Programming Language :: Python :: 3.7
Classifier: Programming Language :: Python :: 3.8
Classifier: Programming Language :: Python :: 3.9
Classifier: Operating System :: OS Independent
Requires-Python: >=3.6
Dynamic: author
Dynamic: author-email
Dynamic: classifier
Dynamic: description
Dynamic: description-content-type
Dynamic: home-page
Dynamic: requires-python
Dynamic: summary
